monterey/__init__.py
monterey/tools/__init__.py
monterey/tools/cli.py
monterey/tools/dialogs.py
monterey/tools/document_reader.py
monterey/tools/frontend.py
monterey/tools/inputs.py
monterey/tools/live_table.py
monterey/tools/loaders.py
monterey/tools/logger.py
monterey/tools/preconditions.py
monterey/tools/progress_bar.py
monterey/tools/tailwind.py
monterey/tools/text.py
monterey/tools/tools.py
monterey-0.0.16.dist-info/METADATA
monterey-0.0.16.dist-info/WHEEL
monterey-0.0.16.dist-info/top_level.txt
monterey-0.0.16.dist-info/RECORD
